README.md
setup.py
specguiutils/__init__.py
specguiutils/counterselector.py
specguiutils/positionerselector.py
specguiutils/radiobuttondelegate.py
specguiutils/scanbrowser.py
specguiutils/scantypeselector.py
specguiutils.egg-info/PKG-INFO
specguiutils.egg-info/SOURCES.txt
specguiutils.egg-info/dependency_links.txt
specguiutils.egg-info/requires.txt
specguiutils.egg-info/top_level.txt
specguiutils/examples/BaseExample.py
specguiutils/examples/__init__.py
specguiutils/examples/counterselectorexample.py
specguiutils/examples/positionerselectorexample.py
specguiutils/examples/scanbrowserexample.py
specguiutils/examples/scantypeselectorexample.py
specguiutils/model/__init__.py
specguiutils/model/counterselectortablemodel.py
specguiutils/test/__init__.py
specguiutils/test/testCounterSelectorModel.py
specguiutils/test/testCounterSelectorView.py
specguiutils/test/testScanBrowser.py
specguiutils/test/testsuite.py
specguiutils/view/__init__.py
specguiutils/view/counterselectorview.py